{"cameraMode":{"drawMode":0,"name":"Shaded","section":"Shading Mode"},"sceneLighting":true,"audioPlay":false,"sceneViewState":{"m_AlwaysRefresh":false,"showFog":true,"showSkybox":true,"showFlares":true,"showImageEffects":true,"showParticleSystems":true,"showVisualEffectGraphs":true,"m_FxEnabled":true},"in2DMode":false,"pivot":{"x":212.34693908691407,"y":10.051078796386719,"z":-5.905708312988281},"rotation":{"x":0.06625895947217941,"y":0.0068873693235218529,"z":-0.000457280344562605,"w":0.9977793097496033},"size":44.654911041259769,"orthographic":false}