{"cameraMode":{"drawMode":0,"name":"Shaded","section":"Shading Mode"},"sceneLighting":true,"audioPlay":false,"sceneViewState":{"m_AlwaysRefresh":false,"showFog":true,"showSkybox":true,"showFlares":true,"showImageEffects":true,"showParticleSystems":true,"showVisualEffectGraphs":true,"m_FxEnabled":true},"in2DMode":false,"pivot":{"x":236.4020538330078,"y":-67.12423706054688,"z":127.03140258789063},"rotation":{"x":-0.1867074817419052,"y":-0.0008880326640792191,"z":0.00016439982573501766,"w":-0.9824190735816956},"size":156.83786010742188,"orthographic":false}